lambdarado/__init__.py
lambdarado/_common.py
lambdarado/_constants.py
lambdarado/_lambdarado.py
lambdarado/_wrap_handler_default.py
lambdarado-2.3.0.post2.dist-info/LICENSE
lambdarado-2.3.0.post2.dist-info/METADATA
lambdarado-2.3.0.post2.dist-info/WHEEL
lambdarado-2.3.0.post2.dist-info/top_level.txt
lambdarado-2.3.0.post2.dist-info/RECORD
