Metadata-Version: 2.1
Name: lambdarado
Version: 2.3.0.post2
Summary: Universal entry point for Docker images containing WSGI apps for the AWS Lambda.
Home-page: https://github.com/rtmigo/lambdarado_py#readme
Author: Artёm IG
Author-email: ortemeo@gmail.com
License: MIT
Keywords: amazon,aws,lambda,function,entrypoint,docker,image,container,wsgi,flask,http,api,gateway,serverless,app
Platform: UNKNOWN
Classifier: Development Status :: 3 - Alpha
Classifier: License :: OSI Approved :: MIT License
Classifier: Programming Language :: Python :: 3.7
Classifier: Programming Language :: Python :: 3.8
Classifier: Programming Language :: Python :: 3.9
Classifier: Programming Language :: Python :: 3.10
Classifier: Operating System :: POSIX
License-File: LICENSE
Requires-Dist: apig-wsgi
Requires-Dist: awslambdaric
Requires-Dist: aws-lambda-context
